desknet/__init__.py
desknet/tests.py
python_desknet-0.0.1.dist-info/DESCRIPTION.rst
python_desknet-0.0.1.dist-info/LICENSE.txt
python_desknet-0.0.1.dist-info/METADATA
python_desknet-0.0.1.dist-info/RECORD
python_desknet-0.0.1.dist-info/WHEEL
python_desknet-0.0.1.dist-info/metadata.json
python_desknet-0.0.1.dist-info/top_level.txt
