Metadata-Version: 2.0
Name: python-desknet
Version: 0.0.1
Summary: A simple Python wrapper for the DeskNet API
Home-page: http://www.github.com/datadesk/python-desknet/
Author: Los Angeles Times Data Desk
Author-email: datadesk@latimes.com
License: MIT
Platform: UNKNOWN
Classifier: Development Status :: 5 - Production/Stable
Classifier: Intended Audience :: Developers
Classifier: Operating System :: OS Independent
Classifier: License :: OSI Approved :: MIT License
Classifier: Programming Language :: Python
Classifier: Programming Language :: Python :: 2
Classifier: Programming Language :: Python :: 2.7
Classifier: Programming Language :: Python :: 3
Classifier: Programming Language :: Python :: 3.5
Classifier: Topic :: Internet :: WWW/HTTP
Requires-Dist: requests
